hprobe-0.2.1.post2.dist-info/METADATA
hprobe-0.2.1.post2.dist-info/WHEEL
hprobe/__init__.py
hprobe/asndata.bin
hprobe/fp_data/fp_rules.json
hprobe/hprobe.pyd
hprobe-0.2.1.post2.dist-info/RECORD
