Metadata-Version: 2.4
Name: hprobe
Version: 0.2.1.post2
Classifier: Programming Language :: Python :: 3
Classifier: Programming Language :: Rust
Classifier: Operating System :: OS Independent
Summary: High-performance HTTP probing engine written in Rust
Keywords: hprobe,wappalyzer,rswappalyzer,fingerprint
Author-email: FlyfishSec <adwinistrator@foxmail.com>
License: MIT
Requires-Python: >=3.7
